tests/__init__.py
tests/test_basic.py
tests/test_transform.py
tiptapy/__init__.py
tiptapy/image.py
tiptapy/macros.py
tiptapy/templates/blockquote.html
tiptapy/templates/bulletList.html
tiptapy/templates/bullet_list.html
tiptapy/templates/codeBlock.html
tiptapy/templates/code_block.html
tiptapy/templates/doc.html
tiptapy/templates/embed.html
tiptapy/templates/hardBreak.html
tiptapy/templates/hard_break.html
tiptapy/templates/heading.html
tiptapy/templates/horizontalRule.html
tiptapy/templates/horizontal_rule.html
tiptapy/templates/image.html
tiptapy/templates/listItem.html
tiptapy/templates/list_item.html
tiptapy/templates/orderedList.html
tiptapy/templates/ordered_list.html
tiptapy/templates/paragraph.html
tiptapy/templates/stack-audio-player.html
tiptapy/templates/stack-document.html
tiptapy/templates/text.html
tiptapy/templates/title.html
tiptapy/templates/extras/audio.html
tiptapy/templates/extras/document.html
tiptapy/templates/extras/featuredimage.html
tiptapy/templates/marks/bold.html
tiptapy/templates/marks/code.html
tiptapy/templates/marks/italic.html
tiptapy/templates/marks/link.html
tiptapy/templates/marks/sup.html
tiptapy/templates/marks/underline.html
tiptapy-0.20.0.dist-info/LICENSE
tiptapy-0.20.0.dist-info/METADATA
tiptapy-0.20.0.dist-info/WHEEL
tiptapy-0.20.0.dist-info/top_level.txt
tiptapy-0.20.0.dist-info/RECORD
