Metadata-Version: 2.1
Name: tiptapy
Version: 0.20.0
Summary: Library that generates HTML output from JSON export of tiptap editor
Home-page: https://github.com/scrolltech/tiptapy
Author: Shekhar Tiwatne
Author-email: pythonic@gmail.com
License: http://www.opensource.org/licenses/mit-license.php
Classifier: Programming Language :: Python :: 3
Classifier: License :: OSI Approved :: MIT License
Classifier: Operating System :: OS Independent
License-File: LICENSE
